Workbook

Sheet Sheet1
A1: cod | B1: texto | C1: categoria_original | D1: carpeta | E1: nombre_carpeta | F1: subcarpeta
A2: 1 | B2: Briefly comment on relevant information about the Bank, coverage and presence in the mentioned markets, key milestones, and recognitions. | C2: 1 | D2: 5 | E2: 1 - santander | F2: =E2 -> 1 - santander
A3: 2 | B3: Bank Background: Describe your global/regional coverage, branch presence and number of years present in each country in scope of this RFP. Provide key indicators of your bank's financial strength and a list of awards or certifications that your bank has received in our region during the last years. | C3: 1 | D3: 5 | E3: 1 - santander | F3: =E3 -> 1 - santander
A4: 3 | B4: Bank Presence in the Region | C4: 1 | D4: 5 | E4: 1 - santander | F4: =E4 -> 1 - santander
A5: 4 | B5: How long has the bank been operating in each country and plans for the future? | C5: 1 | D5: 5 | E5: 1 - santander | F5: =E5 -> 1 - santander
A6: 5 | B6: The main business areas the bank is involved with in these countries | C6: 1 | D6: 5 | E6: 1 - santander | F6: =E6 -> 1 - santander
A7: 6 | B7: The key customer segments the bank targets & differences between these segments | C7: 1 | D7: 5 | E7: 1 - santander | F7: =E7 -> 1 - santander
A8: 7 | B8: Please provide a brief overview of the bank's strategy as it relates to transaction services in LatAm. | C8: 1 | D8: 5 | E8: 1 - santander | F8: =E8 -> 1 - santander
A9: 8 | B9: Detail the nature of your presence in LatAm, i.e. full-service branch, representative office or partner bank. Where partner banks are involved, what services are these banks covering? | C9: 1 | D9: 5 | E9: 1 - santander | F9: =E9 -> 1 - santander
A10: 9 | B10: What is in your view your unique selling point that differentiates you from other banks? | C10: 1 | D10: 5 | E10: 1 - santander | F10: =E10 -> 1 - santander
A11: 10 | B11: LatAm's regulatory environment is ever evolving. How can the bank help S+N take advantage of the opportunities from changes in regulation from the regulatory bodies in order to achieve business and treasury objectives? | C11: 1 | D11: 5 | E11: 1 - santander | F11: =E11 -> 1 - santander
A12: 11 | B12: Describe your scope in the collection service within the local market | C12: 5 | D12: 6 | E12: 2 - coremarkets | F12: =E12 -> 2 - coremarkets
A13: 12 | B13: If a partner bank is utilized for collections, describe how the funds are swept (concentrated) back to your bank, highlighting cut-off times. Specify if there are any funds left in the partner bank's accounts. | C13: 5 | D13: 6 | E13: 2 - coremarkets | F13: =E13 -> 2 - coremarkets
... A39: 38 | B39: Have disaster recovery procedures ever been implemented for a real disaster? | C39: 10 | D39: 3 | E39: 4 - continuidad de negocio | F39: =E39 -> 4 - continuidad de negocio
A40: 39 | B40: Please describe the implementation steps for the bank account and cash pooling structure. Please include in your answer the proposed resources (include names, qualifications, and experiences) from the bank that will support this implementation; people will be dedicated to Disney throughout the project. | C40: 11 | D40: 1 | E40: 3 - nexus | F40: =VLOOKUP(C40,Hoja1!A:B,2,0) -> 4 client service & implementation
A41: 40 | B41: Provide copy or pro-forma of all agreements that will be required to initiate services, account opening and transfer forms. Electronic reporting agreements, set off agreements and pooling arrangements (where appropriate). | C41: 11 | D41: 1 | E41: 3 - nexus | F41: =VLOOKUP(C41,Hoja1!A:B,2,0) -> 4 client service & implementation
A42: 41 | B42: Does the bank provide technical support for hardware, software, and communication problems? Is support documentation for the systems available? | C42: 11 | D42: 1 | E42: 3 - nexus | F42: =VLOOKUP(C42,Hoja1!A:B,2,0) -> 4 client service & implementation
A43: 42 | B43: Based on your bank's experience from completion of implementation projects of a similar scope and nature, do provide a draft project plan detailing anticipated timelines for the project, key milestones, and dependencies. | C43: 11 | D43: 1 | E43: 3 - nexus | F43: =VLOOKUP(C43,Hoja1!A:B,2,0) -> 4 client service & implementation
A44: 43 | B44: What resources (function and number) from Disney should be made available during the implementation? Please specify their responsibilities for the given function and time commitment anticipated. | C44: 11 | D44: 1 | E44: 3 - nexus | F44: =VLOOKUP(C44,Hoja1!A:B,2,0) -> 4 client service & implementation
A45: 44 | B45: Please describe your post implementation services. | C45: 11 | D45: 1 | E45: 3 - nexus | F45: =VLOOKUP(C45,Hoja1!A:B,2,0) -> 4 client service & implementation
A46: 45 | B46: In what languages are user manuals available? | C46: 11 | D46: 1 | E46: 3 - nexus | F46: =VLOOKUP(C46,Hoja1!A:B,2,0) -> 4 client service & implementation
A47: 46 | B47: Please detail the end-user training programs that you offer and the recommended facilities that you would utilize to conduct training. | C47: 11 | D47: 1 | E47: 3 - nexus | F47: =VLOOKUP(C47,Hoja1!A:B,2,0) -> 4 client service & implementation
A48: 47 | B48: Will there be a dedicated implementation team assigned to Smith+Nephew? | C48: 11 | D48: 1 | E48: 3 - nexus | F48: =VLOOKUP(C48,Hoja1!A:B,2,0) -> 4 client service & implementation
A49: 48 | B49: Provide the role profile of a typical Implementation Manager who will manage the project. | C49: 11 | D49: 1 | E49: 3 - nexus | F49: =VLOOKUP(C49,Hoja1!A:B,2,0) -> 4 client service & implementation
A50: 49 | B50: Describe the customer service structure and escalation levels; specify whether it is handled through a centralized account manager or depends on the account’s branch, including the resolution capabilities of this team. If customer service is decentralized, indicate the countries involved and any differences in time zones and language. Also specify the available communication channels and service hours. | C50: 11 | D50: 1 | E50: 3 - nexus | F50: =VLOOKUP(C50,Hoja1!A:B,2,0) -> 4 client service & implementation
A51: 50 | B51: Please describe your bank's customer service organization structure. Please make a distinction between customer service for the central processes and the local Operating Companies. | C51: 11 | D51: 1 | E51: 3 - nexus | F51: =VLOOKUP(C51,Hoja1!A:B,2,0) -> 4 client service & implementation
... A59: 58 | B59: Describe the responsibilities of each representative, and the chain of command and escalation procedure. | C59: 11 | D59: 1 | E59: 3 - nexus | F59: =VLOOKUP(C59,Hoja1!A:B,2,0) -> 4 client service & implementation
A60: 59 | B60: Please comment on long term strategy of your bank regarding cash management services. | C60: 12 | D60: 4 | E60: 5 - innovación | F60: =E60 -> 5 - innovación
A61: 60 | B61: How does your bank provide regulatory updates which are applicable for your clients? | C61: 12 | D61: 4 | E61: 5 - innovación | F61: =E61 -> 5 - innovación
A62: 61 | B62: Discuss the factors that differentiate your service from that of other providers (including new offerings, future developments etc.). | C62: 12 | D62: 4 | E62: 5 - innovación | F62: =E62 -> 5 - innovación
A63: 62 | B63: What is the bank's current strategy towards cash management? How stable is the bank presence in the country in scope of this RFP? | C63: 12 | D63: 4 | E63: 5 - innovación | F63: =E63 -> 5 - innovación
A64: 63 | B64: Please describe recent innovations in Cash management at our bank and how these can benefit our business model. | C64: 12 | D64: 4 | E64: 5 - innovación | F64: =E64 -> 5 - innovación
A65: 64 | B65: How does your bank leverage data analytics, AI, or predictive tools in cash management and payments? | C65: 12 | D65: 4 | E65: 5 - innovación | F65: =E65 -> 5 - innovación
A66: 65 | B66: Describe any emerging technologies in cash management, such as blockchain, AI, and machine learning. | C66: 12 | D66: 4 | E66: 5 - innovación | F66: =E66 -> 5 - innovación
A67: 66 | B67: Please briefly describe your innovation and digital strategy. | C67: 12 | D67: 4 | E67: 5 - innovación | F67: =E67 -> 5 - innovación
A68: 67 | B68: Please describe any recent or future planned innovations/enhanced functionality that you can offer the company. | C68: 12 | D68: 4 | E68: 5 - innovación | F68: =E68 -> 5 - innovación
A69: 68 | B69: Please describe any recent or future use of AI to improve operations or daily activities. | C69: 12 | D69: 4 | E69: 5 - innovación | F69: =E69 -> 5 - innovación
A70: 69 | B70: Please provide details of on-shore and off-shore investment options for local cash, such as Time Deposit, Money Market Funds, etc and indicative rates and minimum amount requirements. Please detail the types of investments and the process, if its automatic investment, per request based and liquidity options. | C70: 9 | D70: 6 | E70: 2 - coremarkets | F70: =E70 -> 2 - coremarkets
A71: 70 | B71: Are there differences in cutoff times for payments initiated manually via EB vs. those sent via SWIFT? | C71: 2 | D71: 1 | E71: 3 - nexus | F71: =VLOOKUP(C71,Hoja1!A:B,2,0) -> 2 nexus hub
A72: 71 | B72: What bank connectivity solutions do you recommend for ADM? | C72: 2 | D72: 1 | E72: 3 - nexus | F72: =VLOOKUP(C72,Hoja1!A:B,2,0) -> 2 nexus hub
A73: 72 | B73: Identify your supported connectivity channels (e.g., SWIFT, SFTP, API). | C73: 2 | D73: 1 | E73: 3 - nexus | F73: =VLOOKUP(C73,Hoja1!A:B,2,0) -> 2 nexus hub
A74: 73 | B74: What XML versions are supported for all payment types? | C74: 2 | D74: 1 | E74: 3 - nexus | F74: =VLOOKUP(C74,Hoja1!A:B,2,0) -> 2 nexus hub
A75: 74 | B75: Can your bank process mixed payment files containing different payment types, currencies, and accounts? | C75: 2 | D75: 1 | E75: 3 - nexus | F75: =VLOOKUP(C75,Hoja1!A:B,2,0) -> 2 nexus hub
A76: 75 | B76: Does your bank provide Customer Payment Status Report (pain.002)? | C76: 2 | D76: 1 | E76: 3 - nexus | F76: =VLOOKUP(C76,Hoja1!A:B,2,0) -> 2 nexus hub
A77: 76 | B77: Describe your duplicate payment handling controls and exception management processes. Does your solution include interface and data transfer controls to detect data loss or corruption? | C77: 2 | D77: 1 | E77: 3 - nexus | F77: =VLOOKUP(C77,Hoja1!A:B,2,0) -> 2 nexus hub
A78: 77 | B78: When does the Bank assume ownership and liability for payment files or messages sent? | C78: 2 | D78: 1 | E78: 3 - nexus | F78: =VLOOKUP(C78,Hoja1!A:B,2,0) -> 2 nexus hub
A79: 78 | B79: Are MT940 statements sent via SWIFT FileAct by account or in bulk? | C79: 2 | D79: 1 | E79: 3 - nexus | F79: =VLOOKUP(C79,Hoja1!A:B,2,0) -> 2 nexus hub
A80: 79 | B80: Detail the timing of account reporting for both in-bank and third-party accounts, also clarifying whether EBICS and SWIFT can be used together. | C80: 2 | D80: 1 | E80: 3 - nexus | F80: =VLOOKUP(C80,Hoja1!A:B,2,0) -> 2 nexus hub
A81: 80 | B81: What TEST environments are available, and do they support Bank-to-Customer Reporting? | C81: 3 | D81: 1 | E81: 3 - nexus | F81: =VLOOKUP(C81,Hoja1!A:B,2,0) -> 3 nexus information center
A82: 81 | B82: Can users independently create, submit, and run projects in the test environment without bank approval? Additionally, does the test environment offer comprehensive reporting capabilities, with automatic email notifications for test results? | C82: 3 | D82: 1 | E82: 3 - nexus | F82: =VLOOKUP(C82,Hoja1!A:B,2,0) -> 3 nexus information center
... A109: 108 | B109: Can you provide an online overview or demo of your EBS for internal stakeholders? A live demonstration may be requested if your bank is shortlisted in the tender process. | C109: 6 | D109: 1 | E109: 3 - nexus | F109: =VLOOKUP(C109,Hoja1!A:B,2,0) -> 3 nexus global portal
A110: 109 | B110: Describe your cross-border payments solutions. How will you support regulatory reporting requirements (if required)? | C110: 13 | D110: 6 | E110: 2 - coremarkets | F110: =E110 -> 2 - coremarkets
A111: 110 | B111: Do you have paperless solutions to perform supporting documents validation of cross-border payments? | C111: 13 | D111: 6 | E111: 2 - coremarkets | F111: =E111 -> 2 - coremarkets
A112: 111 | B112: Do you have any simplification solution to simplify supporting documents validation of cross-border payments? | C112: 13 | D112: 6 | E112: 2 - coremarkets | F112: =E112 -> 2 - coremarkets
A113: 112 | B113: At what point is the FX rate set (at initiation of the payment or release)? | C113: 13 | D113: 6 | E113: 2 - coremarkets | F113: =E113 -> 2 - coremarkets
A114: 113 | B114: How are rates determined? Does your bank offer competitive FX rates taking into account the global relationship of the client? | C114: 13 | D114: 6 | E114: 2 - coremarkets | F114: =E114 -> 2 - coremarkets
A115: 114 | B115: Please list the reference rates, margins and calculations used for cross-currency payments. | C115: 13 | D115: 6 | E115: 2 - coremarkets | F115: =E115 -> 2 - coremarkets
A116: 115 | B116: What document delivery methods can your bank accept for general account services (bank account opening, KYC, mandates e.g. Hard copy, scanned copy via email, e-signatures platforms)? | C116: 14 | D116: 6 | E116: 2 - coremarkets | F116: =E116 -> 2 - coremarkets
A117: 116 | B117: How long does an account opening process incl. KYC take after submission of all documents (days)? | C117: 14 | D117: 6 | E117: 2 - coremarkets | F117: =E117 -> 2 - coremarkets
A118: 117 | B118: A clear list of all documentation required by the bank is to be provided, to: initiate the business relationship and to open bank accounts. | C118: 14 | D118: 6 | E118: 2 - coremarkets | F118: =E118 -> 2 - coremarkets
A119: 118 | B119: Please list all the agreements that will be required to initiate services and perform the KYC process, highlighting any areas where this is not standardized across the relationship. | C119: 14 | D119: 6 | E119: 2 - coremarkets | F119: =E119 -> 2 - coremarkets
A120: 119 | B120: Please describe how the bank will help to facilitate the documentation process and how you will guide S+N through this. | C120: 14 | D120: 6 | E120: 2 - coremarkets | F120: =E120 -> 2 - coremarkets
A121: 120 | B121: How will the bank facilitate ongoing KYC requirements? | C121: 14 | D121: 6 | E121: 2 - coremarkets | F121: =E121 -> 2 - coremarkets
... A123: 122 | B123: Specify any solutions to make documentation more efficient (e.g. e-signatures, etc.) | C123: 14 | D123: 6 | E123: 2 - coremarkets | F123: =E123 -> 2 - coremarkets
B124: Account opening requirements for each country in scope | C124: 14 | D124: 6 | E124: 2 - coremarkets | F124: =E124 -> 2 - coremarkets
B125: Are wet signatures mandatory, or are digital signatures allowed | C125: 14 | D125: 6 | E125: 2 - coremarkets | F125: =E125 -> 2 - coremarkets

Sheet Hoja1
A1: categoria_original
A2: 1
A3: 2 | B3: 2 nexus hub
A4: 3 | B4: 3 nexus information center
A5: 4 | B5: 2 nexus hub o 3 nexus global portal
A6: 5
A7: 6 | B7: 3 nexus global portal
A8: 7
A9: 8
A10: 9
A11: 10
A12: 11 | B12: 4 client service & implementation
A13: 12
A14: 13
A15: 14
